small_ass_cache/__init__.py
small_ass_cache/small_ass_cache.py
small_ass_cache-0.9.2.dist-info/LICENSE
small_ass_cache-0.9.2.dist-info/METADATA
small_ass_cache-0.9.2.dist-info/WHEEL
small_ass_cache-0.9.2.dist-info/top_level.txt
small_ass_cache-0.9.2.dist-info/RECORD
