Metadata-Version: 2.1
Name: small-ass-cache
Version: 0.9.2
Summary: An asset loading and caching utility for game assets.
Home-page: https://github.com/wegfawefgawefg/small-ass-cache
Author: Gibson Martin
Author-email: 668es218pur@gmail.com
License: GPLv3
Classifier: Programming Language :: Python :: 3
Classifier: License :: OSI Approved :: GNU General Public License v3 (GPLv3)
Classifier: Development Status :: 4 - Beta
Classifier: Topic :: Games/Entertainment
Classifier: Topic :: Utilities
Requires-Python: >=3.6
License-File: LICENSE
